[
  {
    "description": "  As a user\n  I want to view JetBrains projects on the homepage\n  So that I can explore the JetBrains projects found on my system",
    "elements": [
      {
        "description": "",
        "id": "homepage;homepage-title",
        "keyword": "Scenario",
        "line": 11,
        "name": "Homepage title",
        "steps": [
          {
            "keyword": "Before",
            "hidden": true,
            "result": {
              "status": "passed",
              "duration": 176610374
            }
          },
          {
            "arguments": [],
            "keyword": "Given ",
            "line": 7,
            "name": "the application has access to the JetBrains logs directory",
            "match": {
              "location": "file:/Users/dmeehan/Library/CloudStorage/Dropbox/Projects/JetBrains/junie-explorer/features/step_definitions/homepage.steps.ts:4"
            },
            "result": {
              "status": "passed",
              "duration": 771125
            }
          },
          {
            "arguments": [],
            "keyword": "And ",
            "line": 8,
            "name": "the user has a web browser",
            "match": {
              "location": "file:/Users/dmeehan/Library/CloudStorage/Dropbox/Projects/JetBrains/junie-explorer/features/step_definitions/homepage.steps.ts:10"
            },
            "result": {
              "status": "passed",
              "duration": 237417
            }
          },
          {
            "arguments": [],
            "keyword": "Given ",
            "line": 12,
            "name": "there are JetBrains projects in the logs",
            "match": {
              "location": "file:/Users/dmeehan/Library/CloudStorage/Dropbox/Projects/JetBrains/junie-explorer/features/step_definitions/homepage.steps.ts:16"
            },
            "result": {
              "status": "passed",
              "duration": 232416
            }
          },
          {
            "arguments": [],
            "keyword": "When ",
            "line": 13,
            "name": "the user visits the homepage",
            "match": {
              "location": "file:/Users/dmeehan/Library/CloudStorage/Dropbox/Projects/JetBrains/junie-explorer/features/step_definitions/homepage.steps.ts:22"
            },
            "result": {
              "status": "passed",
              "duration": 674063582
            }
          },
          {
            "arguments": [],
            "keyword": "Then ",
            "line": 14,
            "name": "the user should see a page titled \"Junie Explorer\"",
            "match": {
              "location": "file:/Users/dmeehan/Library/CloudStorage/Dropbox/Projects/JetBrains/junie-explorer/features/step_definitions/homepage.steps.ts:29"
            },
            "result": {
              "status": "passed",
              "duration": 7723124
            }
          },
          {
            "keyword": "After",
            "hidden": true,
            "result": {
              "status": "passed",
              "duration": 29773292
            }
          }
        ],
        "tags": [
          {
            "name": "@wip",
            "line": 10
          }
        ],
        "type": "scenario"
      },
      {
        "description": "",
        "id": "homepage;logs-directory-path-display",
        "keyword": "Scenario",
        "line": 17,
        "name": "Logs directory path display",
        "steps": [
          {
            "keyword": "Before",
            "hidden": true,
            "result": {
              "status": "passed",
              "duration": 166161874
            }
          },
          {
            "arguments": [],
            "keyword": "Given ",
            "line": 7,
            "name": "the application has access to the JetBrains logs directory",
            "match": {
              "location": "file:/Users/dmeehan/Library/CloudStorage/Dropbox/Projects/JetBrains/junie-explorer/features/step_definitions/homepage.steps.ts:4"
            },
            "result": {
              "status": "passed",
              "duration": 312542
            }
          },
          {
            "arguments": [],
            "keyword": "And ",
            "line": 8,
            "name": "the user has a web browser",
            "match": {
              "location": "file:/Users/dmeehan/Library/CloudStorage/Dropbox/Projects/JetBrains/junie-explorer/features/step_definitions/homepage.steps.ts:10"
            },
            "result": {
              "status": "passed",
              "duration": 263291
            }
          },
          {
            "arguments": [],
            "keyword": "Given ",
            "line": 18,
            "name": "there are JetBrains projects in the logs",
            "match": {
              "location": "file:/Users/dmeehan/Library/CloudStorage/Dropbox/Projects/JetBrains/junie-explorer/features/step_definitions/homepage.steps.ts:16"
            },
            "result": {
              "status": "passed",
              "duration": 196374
            }
          },
          {
            "arguments": [],
            "keyword": "When ",
            "line": 19,
            "name": "the user visits the homepage",
            "match": {
              "location": "file:/Users/dmeehan/Library/CloudStorage/Dropbox/Projects/JetBrains/junie-explorer/features/step_definitions/homepage.steps.ts:22"
            },
            "result": {
              "status": "passed",
              "duration": 700778333
            }
          },
          {
            "arguments": [],
            "keyword": "Then ",
            "line": 20,
            "name": "the user should see the path to the JetBrains logs directory",
            "match": {
              "location": "file:/Users/dmeehan/Library/CloudStorage/Dropbox/Projects/JetBrains/junie-explorer/features/step_definitions/homepage.steps.ts:37"
            },
            "result": {
              "status": "failed",
              "duration": 23084959,
              "error_message": "Error: \u001b[2mexpect(\u001b[22m\u001b[31mreceived\u001b[39m\u001b[2m).\u001b[22mtoBe\u001b[2m(\u001b[22m\u001b[32mexpected\u001b[39m\u001b[2m) // Object.is equality\u001b[22m\n\nExpected: \u001b[32mtrue\u001b[39m\nReceived: \u001b[31mfalse\u001b[39m\n    at Proxy.<anonymous> (/Users/dmeehan/Library/CloudStorage/Dropbox/Projects/JetBrains/junie-explorer/node_modules/playwright/lib/matchers/expect.js:221:24)\n    at CustomWorld.<anonymous> (file:///Users/dmeehan/Library/CloudStorage/Dropbox/Projects/JetBrains/junie-explorer/features/step_definitions/homepage.steps.ts:42:23)"
            }
          },
          {
            "keyword": "After",
            "hidden": true,
            "result": {
              "status": "passed",
              "duration": 32226000
            }
          }
        ],
        "tags": [
          {
            "name": "@wip",
            "line": 16
          }
        ],
        "type": "scenario"
      },
      {
        "description": "",
        "id": "homepage;projects-list-display",
        "keyword": "Scenario",
        "line": 23,
        "name": "Projects list display",
        "steps": [
          {
            "keyword": "Before",
            "hidden": true,
            "result": {
              "status": "passed",
              "duration": 163208499
            }
          },
          {
            "arguments": [],
            "keyword": "Given ",
            "line": 7,
            "name": "the application has access to the JetBrains logs directory",
            "match": {
              "location": "file:/Users/dmeehan/Library/CloudStorage/Dropbox/Projects/JetBrains/junie-explorer/features/step_definitions/homepage.steps.ts:4"
            },
            "result": {
              "status": "passed",
              "duration": 170750
            }
          },
          {
            "arguments": [],
            "keyword": "And ",
            "line": 8,
            "name": "the user has a web browser",
            "match": {
              "location": "file:/Users/dmeehan/Library/CloudStorage/Dropbox/Projects/JetBrains/junie-explorer/features/step_definitions/homepage.steps.ts:10"
            },
            "result": {
              "status": "passed",
              "duration": 149957
            }
          },
          {
            "arguments": [],
            "keyword": "Given ",
            "line": 24,
            "name": "there are JetBrains projects in the logs",
            "match": {
              "location": "file:/Users/dmeehan/Library/CloudStorage/Dropbox/Projects/JetBrains/junie-explorer/features/step_definitions/homepage.steps.ts:16"
            },
            "result": {
              "status": "passed",
              "duration": 76082
            }
          },
          {
            "arguments": [],
            "keyword": "When ",
            "line": 25,
            "name": "the user visits the homepage",
            "match": {
              "location": "file:/Users/dmeehan/Library/CloudStorage/Dropbox/Projects/JetBrains/junie-explorer/features/step_definitions/homepage.steps.ts:22"
            },
            "result": {
              "status": "passed",
              "duration": 672705624
            }
          },
          {
            "arguments": [],
            "keyword": "Then ",
            "line": 26,
            "name": "the user should see a list of all JetBrains projects",
            "match": {
              "location": "file:/Users/dmeehan/Library/CloudStorage/Dropbox/Projects/JetBrains/junie-explorer/features/step_definitions/homepage.steps.ts:45"
            },
            "result": {
              "status": "failed",
              "duration": 18034625,
              "error_message": "Error: \u001b[2mexpect(\u001b[22m\u001b[31mreceived\u001b[39m\u001b[2m).\u001b[22mtoBe\u001b[2m(\u001b[22m\u001b[32mexpected\u001b[39m\u001b[2m) // Object.is equality\u001b[22m\n\nExpected: \u001b[32mtrue\u001b[39m\nReceived: \u001b[31mfalse\u001b[39m\n    at Proxy.<anonymous> (/Users/dmeehan/Library/CloudStorage/Dropbox/Projects/JetBrains/junie-explorer/node_modules/playwright/lib/matchers/expect.js:221:24)\n    at CustomWorld.<anonymous> (file:///Users/dmeehan/Library/CloudStorage/Dropbox/Projects/JetBrains/junie-explorer/features/step_definitions/homepage.steps.ts:50:23)"
            }
          },
          {
            "keyword": "After",
            "hidden": true,
            "result": {
              "status": "passed",
              "duration": 19523624
            }
          }
        ],
        "tags": [
          {
            "name": "@wip",
            "line": 22
          }
        ],
        "type": "scenario"
      },
      {
        "description": "",
        "id": "homepage;project-name-display",
        "keyword": "Scenario",
        "line": 29,
        "name": "Project name display",
        "steps": [
          {
            "keyword": "Before",
            "hidden": true,
            "result": {
              "status": "passed",
              "duration": 156856957
            }
          },
          {
            "arguments": [],
            "keyword": "Given ",
            "line": 7,
            "name": "the application has access to the JetBrains logs directory",
            "match": {
              "location": "file:/Users/dmeehan/Library/CloudStorage/Dropbox/Projects/JetBrains/junie-explorer/features/step_definitions/homepage.steps.ts:4"
            },
            "result": {
              "status": "passed",
              "duration": 213250
            }
          },
          {
            "arguments": [],
            "keyword": "And ",
            "line": 8,
            "name": "the user has a web browser",
            "match": {
              "location": "file:/Users/dmeehan/Library/CloudStorage/Dropbox/Projects/JetBrains/junie-explorer/features/step_definitions/homepage.steps.ts:10"
            },
            "result": {
              "status": "passed",
              "duration": 184625
            }
          },
          {
            "arguments": [],
            "keyword": "Given ",
            "line": 30,
            "name": "there are JetBrains projects in the logs",
            "match": {
              "location": "file:/Users/dmeehan/Library/CloudStorage/Dropbox/Projects/JetBrains/junie-explorer/features/step_definitions/homepage.steps.ts:16"
            },
            "result": {
              "status": "passed",
              "duration": 103292
            }
          },
          {
            "arguments": [],
            "keyword": "When ",
            "line": 31,
            "name": "the user visits the homepage",
            "match": {
              "location": "file:/Users/dmeehan/Library/CloudStorage/Dropbox/Projects/JetBrains/junie-explorer/features/step_definitions/homepage.steps.ts:22"
            },
            "result": {
              "status": "passed",
              "duration": 677535292
            }
          },
          {
            "arguments": [],
            "keyword": "Then ",
            "line": 32,
            "name": "each project should display its name",
            "match": {
              "location": "file:/Users/dmeehan/Library/CloudStorage/Dropbox/Projects/JetBrains/junie-explorer/features/step_definitions/homepage.steps.ts:55"
            },
            "result": {
              "status": "failed",
              "duration": 18600916,
              "error_message": "Error: \u001b[2mexpect(\u001b[22m\u001b[31mreceived\u001b[39m\u001b[2m).\u001b[22mtoBe\u001b[2m(\u001b[22m\u001b[32mexpected\u001b[39m\u001b[2m) // Object.is equality\u001b[22m\n\nExpected: \u001b[32mtrue\u001b[39m\nReceived: \u001b[31mfalse\u001b[39m\n    at Proxy.<anonymous> (/Users/dmeehan/Library/CloudStorage/Dropbox/Projects/JetBrains/junie-explorer/node_modules/playwright/lib/matchers/expect.js:221:24)\n    at CustomWorld.<anonymous> (file:///Users/dmeehan/Library/CloudStorage/Dropbox/Projects/JetBrains/junie-explorer/features/step_definitions/homepage.steps.ts:60:29)"
            }
          },
          {
            "keyword": "After",
            "hidden": true,
            "result": {
              "status": "passed",
              "duration": 18819708
            }
          }
        ],
        "tags": [
          {
            "name": "@wip",
            "line": 28
          }
        ],
        "type": "scenario"
      },
      {
        "description": "",
        "id": "homepage;ide-icons-display",
        "keyword": "Scenario",
        "line": 35,
        "name": "IDE icons display",
        "steps": [
          {
            "keyword": "Before",
            "hidden": true,
            "result": {
              "status": "passed",
              "duration": 162556000
            }
          },
          {
            "arguments": [],
            "keyword": "Given ",
            "line": 7,
            "name": "the application has access to the JetBrains logs directory",
            "match": {
              "location": "file:/Users/dmeehan/Library/CloudStorage/Dropbox/Projects/JetBrains/junie-explorer/features/step_definitions/homepage.steps.ts:4"
            },
            "result": {
              "status": "passed",
              "duration": 154166
            }
          },
          {
            "arguments": [],
            "keyword": "And ",
            "line": 8,
            "name": "the user has a web browser",
            "match": {
              "location": "file:/Users/dmeehan/Library/CloudStorage/Dropbox/Projects/JetBrains/junie-explorer/features/step_definitions/homepage.steps.ts:10"
            },
            "result": {
              "status": "passed",
              "duration": 169375
            }
          },
          {
            "arguments": [],
            "keyword": "Given ",
            "line": 36,
            "name": "there are JetBrains projects in the logs",
            "match": {
              "location": "file:/Users/dmeehan/Library/CloudStorage/Dropbox/Projects/JetBrains/junie-explorer/features/step_definitions/homepage.steps.ts:16"
            },
            "result": {
              "status": "passed",
              "duration": 79124
            }
          },
          {
            "arguments": [],
            "keyword": "When ",
            "line": 37,
            "name": "the user visits the homepage",
            "match": {
              "location": "file:/Users/dmeehan/Library/CloudStorage/Dropbox/Projects/JetBrains/junie-explorer/features/step_definitions/homepage.steps.ts:22"
            },
            "result": {
              "status": "passed",
              "duration": 692594708
            }
          },
          {
            "arguments": [],
            "keyword": "Then ",
            "line": 38,
            "name": "each project should display icons for the IDEs it was used with",
            "match": {
              "location": "file:/Users/dmeehan/Library/CloudStorage/Dropbox/Projects/JetBrains/junie-explorer/features/step_definitions/homepage.steps.ts:63"
            },
            "result": {
              "status": "failed",
              "duration": 21259500,
              "error_message": "Error: \u001b[2mexpect(\u001b[22m\u001b[31mreceived\u001b[39m\u001b[2m).\u001b[22mtoBe\u001b[2m(\u001b[22m\u001b[32mexpected\u001b[39m\u001b[2m) // Object.is equality\u001b[22m\n\nExpected: \u001b[32mtrue\u001b[39m\nReceived: \u001b[31mfalse\u001b[39m\n    at Proxy.<anonymous> (/Users/dmeehan/Library/CloudStorage/Dropbox/Projects/JetBrains/junie-explorer/node_modules/playwright/lib/matchers/expect.js:221:24)\n    at CustomWorld.<anonymous> (file:///Users/dmeehan/Library/CloudStorage/Dropbox/Projects/JetBrains/junie-explorer/features/step_definitions/homepage.steps.ts:68:29)"
            }
          },
          {
            "keyword": "After",
            "hidden": true,
            "result": {
              "status": "passed",
              "duration": 17230333
            }
          }
        ],
        "tags": [
          {
            "name": "@wip",
            "line": 34
          }
        ],
        "type": "scenario"
      },
      {
        "description": "",
        "id": "homepage;reload-button-display",
        "keyword": "Scenario",
        "line": 41,
        "name": "Reload button display",
        "steps": [
          {
            "keyword": "Before",
            "hidden": true,
            "result": {
              "status": "passed",
              "duration": 172110832
            }
          },
          {
            "arguments": [],
            "keyword": "Given ",
            "line": 7,
            "name": "the application has access to the JetBrains logs directory",
            "match": {
              "location": "file:/Users/dmeehan/Library/CloudStorage/Dropbox/Projects/JetBrains/junie-explorer/features/step_definitions/homepage.steps.ts:4"
            },
            "result": {
              "status": "passed",
              "duration": 185207
            }
          },
          {
            "arguments": [],
            "keyword": "And ",
            "line": 8,
            "name": "the user has a web browser",
            "match": {
              "location": "file:/Users/dmeehan/Library/CloudStorage/Dropbox/Projects/JetBrains/junie-explorer/features/step_definitions/homepage.steps.ts:10"
            },
            "result": {
              "status": "passed",
              "duration": 223167
            }
          },
          {
            "arguments": [],
            "keyword": "Given ",
            "line": 42,
            "name": "there are JetBrains projects in the logs",
            "match": {
              "location": "file:/Users/dmeehan/Library/CloudStorage/Dropbox/Projects/JetBrains/junie-explorer/features/step_definitions/homepage.steps.ts:16"
            },
            "result": {
              "status": "passed",
              "duration": 114582
            }
          },
          {
            "arguments": [],
            "keyword": "When ",
            "line": 43,
            "name": "the user visits the homepage",
            "match": {
              "location": "file:/Users/dmeehan/Library/CloudStorage/Dropbox/Projects/JetBrains/junie-explorer/features/step_definitions/homepage.steps.ts:22"
            },
            "result": {
              "status": "passed",
              "duration": 704054333
            }
          },
          {
            "arguments": [],
            "keyword": "Then ",
            "line": 44,
            "name": "the user should see a reload button in the header",
            "match": {
              "location": "file:/Users/dmeehan/Library/CloudStorage/Dropbox/Projects/JetBrains/junie-explorer/features/step_definitions/homepage.steps.ts:71"
            },
            "result": {
              "status": "failed",
              "duration": 17527708,
              "error_message": "Error: \u001b[2mexpect(\u001b[22m\u001b[31mreceived\u001b[39m\u001b[2m).\u001b[22mtoBe\u001b[2m(\u001b[22m\u001b[32mexpected\u001b[39m\u001b[2m) // Object.is equality\u001b[22m\n\nExpected: \u001b[32mtrue\u001b[39m\nReceived: \u001b[31mfalse\u001b[39m\n    at Proxy.<anonymous> (/Users/dmeehan/Library/CloudStorage/Dropbox/Projects/JetBrains/junie-explorer/node_modules/playwright/lib/matchers/expect.js:221:24)\n    at CustomWorld.<anonymous> (file:///Users/dmeehan/Library/CloudStorage/Dropbox/Projects/JetBrains/junie-explorer/features/step_definitions/homepage.steps.ts:76:23)"
            }
          },
          {
            "keyword": "After",
            "hidden": true,
            "result": {
              "status": "passed",
              "duration": 18620957
            }
          }
        ],
        "tags": [
          {
            "name": "@wip",
            "line": 40
          }
        ],
        "type": "scenario"
      }
    ],
    "id": "homepage",
    "line": 1,
    "keyword": "Feature",
    "name": "Homepage",
    "tags": [],
    "uri": "features/homepage.feature"
  }
]